kdumpling/__init__.py
kdumpling/builder.py
kdumpling/cpu_context.py
kdumpling/elf.py
kdumpling/kdump_compressed.py
kdumpling/py.typed
kdumpling-0.4.0.dist-info/licenses/LICENSE
kdumpling-0.4.0.dist-info/METADATA
kdumpling-0.4.0.dist-info/WHEEL
kdumpling-0.4.0.dist-info/top_level.txt
kdumpling-0.4.0.dist-info/RECORD
