Metadata-Version: 2.4
Name: kdumpling
Version: 0.4.0
Summary: A Python library for creating Linux kdump crash dump files
License: MIT
Project-URL: Homepage, https://github.com/sdimitro/kdumpling
Project-URL: Repository, https://github.com/sdimitro/kdumpling
Keywords: kdump,vmcore,linux,crash,elf,coredump
Classifier: Development Status :: 5 - Production/Stable
Classifier: Intended Audience :: Developers
Classifier: License :: OSI Approved :: MIT License
Classifier: Operating System :: OS Independent
Classifier: Programming Language :: Python :: 3
Classifier: Programming Language :: Python :: 3.8
Classifier: Programming Language :: Python :: 3.9
Classifier: Programming Language :: Python :: 3.10
Classifier: Programming Language :: Python :: 3.11
Classifier: Programming Language :: Python :: 3.12
Classifier: Topic :: System :: Operating System Kernels :: Linux
Classifier: Topic :: Software Development :: Libraries :: Python Modules
Requires-Python: >=3.8
License-File: LICENSE
Provides-Extra: dev
Requires-Dist: pytest>=7.0; extra == "dev"
Requires-Dist: pyelftools>=0.29; extra == "dev"
Requires-Dist: mypy>=1.0; extra == "dev"
Requires-Dist: ruff>=0.1.0; extra == "dev"
Requires-Dist: drgn>=0.0.25; extra == "dev"
Dynamic: license-file
